<?xml version="1.0" encoding="utf-8"?>
<LanguageData>

  <SolarFlare.label>Badai Matahari</SolarFlare.label> 
  <SolarFlare.description>Badai matahari telah menghantam planet ini. Itu membuat sebagian besar perangkat listrik tidak bekerja dikarenakan interferensi elektromagnetik.</SolarFlare.description>
  <SolarFlare.endMessage>Badai Matahari Telah Berakhir.</SolarFlare.endMessage>

  <Eclipse.label>Gerhana</Eclipse.label>
  <Eclipse.description>Gerhana akan membuat permukaan planet ditutupi dengan kegelapan, bahkan pada saat siang hari.</Eclipse.description>
  <Eclipse.endMessage>Gerhana Telah Berakhir.</Eclipse.endMessage>

  <PsychicDrone.label>Drone Psikis</PsychicDrone.label>
  <PsychicDrone.description>Sebuah AI yang jauh dan kuat mengeluarkan gelombang kekuatan psikis yang mendorong orang menuju kegilaan.</PsychicDrone.description>
  <PsychicDrone.endMessage>Drone Psikis Telah Berakhir.</PsychicDrone.endMessage>

  <PsychicSoothe.label>Ketenangan Psikis</PsychicSoothe.label>
  <PsychicSoothe.description>Sebuah AI yang jauh dan kuat mengeluarkan gelombang kekuatan psikis yang menenangkan orang dan menstabilkan pikiran mereka.</PsychicSoothe.description>
  <PsychicSoothe.endMessage>Ketenangan Psikis Telah Berakhir.</PsychicSoothe.endMessage>

  <ToxicFallout.label>Hujan Debu Beracun</ToxicFallout.label>
  <ToxicFallout.description>Sebuah plume debu beracun dari sumber yang jauh sedang perlahan-lahan mengendap di seluruh wilayah ini. Setiap makhluk hidup yang tidak berada di bawah atap akan perlahan-lahan terpapar racun, dan barang-barang yang ditinggalkan di luar akan mengalami korosi</ToxicFallout.description>
  <ToxicFallout.endMessage>Hujan Debu Beracun Telah Mereda.</ToxicFallout.endMessage>

  <VolcanicWinter.label>Musim Dingin Vulkanik</VolcanicWinter.label>
  <VolcanicWinter.description>Sebuah gunung berapi yang jauh telah menghambat atmosfer dengan partikel vulkanik, secara signifikan mengurangi jumlah cahaya yang mencapai permukaan. Suhu akan lebih dingin dan tanaman akan tumbuh lebih lambat.</VolcanicWinter.description>
  <VolcanicWinter.endMessage>Sebagian besar abu vulkanik telah mengendap.</VolcanicWinter.endMessage>

  <HeatWave.label>Gelombang Panas</HeatWave.label>
  <HeatWave.description>Sebuah gelombang panas yang ekstrem sedang "memanggang" daerah ini.</HeatWave.description>
  <HeatWave.endMessage>Gelombang Panas Sudah Berakhir.</HeatWave.endMessage>

  <ColdSnap.label>Gelombang Dingin</ColdSnap.label>
  <ColdSnap.description>Sebuah gelombang dingin sedang "membekukan" daerah ini.</ColdSnap.description>
  <ColdSnap.endMessage>Gelombang Dingin Sudah Berakhir.</ColdSnap.endMessage>

  <Flashstorm.label>Badai Petir</Flashstorm.label>
  <Flashstorm.description>Sebuah badai lokal yang aneh sedang menghantam area kecil dengan serangan petir berulang.</Flashstorm.description>
  <Flashstorm.endMessage>Badai petir telah berakhir.</Flashstorm.endMessage>

  <ClimateCycle.label>Siklus Iklim</ClimateCycle.label>
  <ClimateCycle.description>Siklus iklim multi-tahun akibat orbit elips.</ClimateCycle.description>

  <Planetkiller.label>Planetkiller</Planetkiller.label>
  <Planetkiller.description>Planetkiller: Senjata pembunuh planet antarbintang mendekati planet ini. Senjata ini akan menghancurkan planet seperti peluru senapan yang mengenai telur, memusnahkan seluruh kehidupan.</Planetkiller.description>

  <Aurora.label>Aurora</Aurora.label>
  <Aurora.description>Sebuah aurora menerangi langit. Tampilan yang memukau ini akan meningkatkan suasana hati siapa pun yang berada di luar untuk melihatnya.</Aurora.description>
  <Aurora.endMessage>"Pertunjukkan" aurora telah berakhir.</Aurora.endMessage>


</LanguageData>
